{"name": "Fat Burner Pro", "hook": "Melt fat in 30 days or your money back", "platform": "Instagram", "content": "Short-form video ad", "assets": {"landing_page": {"headline": "Unleash Your Ultimate Physique with Fat Burner Pro", "benefits": ["Accelerates your body's fat-burning process", "Formulated with natural, scientifically-backed ingredients", "Boosts metabolism and energy levels", "Reduces appetite and helps control cravings", "See noticeable results within 30 days"], "CTA": "Start Your Risk-Free Trial Today!"}, "ad_hooks": ["Ready to torch fat like never before? Fat Burner Pro guarantees results in 30 days or your money back!", "Transform your body with a click! Discover how Fat Burner Pro can melt away your stubborn fat in just 30 days.", "Don't miss out on your dream body! Our 30-day fat loss challenge is on. Are you in? Try Fat Burner Pro now!"], "sales_email": "Are you struggling to shed those extra pounds? Fat Burner Pro is here to ignite your weight loss journey and guarantee visible results in 30 days, or we'll refund your purchase. No gimmicks, just results. Say goodbye to stubborn fat and hello to a new, confident you. Try it risk-free today!"}}
